{"_type":"export","__export_format":4,"__export_date":"2021-05-17T02:36:28.194Z","__export_source":"insomnia.desktop.app:v2021.3.0","resources":[{"_id":"req_1d0c8acedc1941a490b063cee581e0db","parentId":"fld_d7ea4760478a49c0be690dcdb9780a6b","modified":1621215643609,"created":1621214423563,"url":"http://{{ _.server }}:{{ _.puerto }}/api/pedido","name":"01-CrearPedido","description":"","method":"POST","body":{"mimeType":"application/json","text":"{\n  \"detalle\": [\n    {\n      \"cantidad\": 100,\n      \"precio\": 0,\n      \"producto\": {\n        \"descripcion\": \"descripcion material\",\n        \"id\": 1,\n        \"precio\": 1000\n      }\n    }\n  ],\n  \"obra\": {\n    \"descripcion\": \"vial\",\n    \"id\": 1\n  }\n}"},"parameters":[],"headers":[{"name":"Content-Type","value":"application/json","id":"pair_4dfec63a96d648b7a2f198a30ae5f53e"}],"authentication":{},"metaSortKey":-1621214423563,"isPrivate":false,"settingStoreCookies":true,"settingSendCookies":true,"settingDisableRenderRequestBody":false,"settingEncodeUrl":true,"settingRebuildPath":true,"settingFollowRedirects":"global","_type":"request"},{"_id":"fld_d7ea4760478a49c0be690dcdb9780a6b","parentId":"wrk_54d68373d3bd40dbba37866c210345ec","modified":1621213069363,"created":1621213069363,"name":"MS-Pedido","description":"","environment":{},"environmentPropertyOrder":null,"metaSortKey":-1621213069363,"_type":"request_group"},{"_id":"wrk_54d68373d3bd40dbba37866c210345ec","parentId":null,"modified":1616439758313,"created":1616439695943,"name":"DAN_2021","description":"","scope":"collection","_type":"workspace"},{"_id":"req_2397c224abd24e20b4e0d10b2a3b9994","parentId":"fld_d7ea4760478a49c0be690dcdb9780a6b","modified":1621215853109,"created":1621215845024,"url":"http://{{ _.server }}:{{ _.puerto }}/api/pedido","name":"02-ListaPedidos","description":"","method":"GET","body":{},"parameters":[],"headers":[],"authentication":{},"metaSortKey":-1621072273697.5,"isPrivate":false,"settingStoreCookies":true,"settingSendCookies":true,"settingDisableRenderRequestBody":false,"settingEncodeUrl":true,"settingRebuildPath":true,"settingFollowRedirects":"global","_type":"request"},{"_id":"req_8f1d0f46777d4737afd20237f6f89dd2","parentId":"fld_d7ea4760478a49c0be690dcdb9780a6b","modified":1621216470487,"created":1621216190778,"url":"http://{{ _.server }}:{{ _.puerto }}/api/pedido/1","name":"03-ActualizarPedido","description":"","method":"PUT","body":{"mimeType":"application/json","text":"{\n  \"fechaPedido\": \"2021-05-17T01:52:32.089218Z\",\n  \"obra\": {\n    \"id\": 1,\n    \"descripcion\": \"vial\"\n  },\n  \"detalle\": [\n    {\n      \"id\": 1,\n      \"cantidad\": 100,\n      \"precio\": 0.0,\n      \"producto\": {\n        \"id\": 1,\n        \"descripcion\": \"descripcion material\",\n        \"precio\": 1000.0\n      }\n    }\n  ],\n  \"estado\": \"CONFIRMADO\"\n}"},"parameters":[],"headers":[{"name":"Content-Type","value":"application/json","id":"pair_4dfec63a96d648b7a2f198a30ae5f53e"}],"authentication":{},"metaSortKey":-1621072273647.5,"isPrivate":false,"settingStoreCookies":true,"settingSendCookies":true,"settingDisableRenderRequestBody":false,"settingEncodeUrl":true,"settingRebuildPath":true,"settingFollowRedirects":"global","_type":"request"},{"_id":"req_7fda62b07f0746bbb948a027f1d9ea94","parentId":"fld_d7ea4760478a49c0be690dcdb9780a6b","modified":1621217521623,"created":1621217504474,"url":"http://{{ _.server }}:{{ _.puerto }}/api/pedido/1","name":"04-BorrarPedido","description":"","method":"DELETE","body":{},"parameters":[],"headers":[],"authentication":{},"metaSortKey":-1621001198739.75,"isPrivate":false,"settingStoreCookies":true,"settingSendCookies":true,"settingDisableRenderRequestBody":false,"settingEncodeUrl":true,"settingRebuildPath":true,"settingFollowRedirects":"global","_type":"request"},{"_id":"req_62d5b2d8ef4941008da4283e9dd60efd","parentId":"fld_d7ea4760478a49c0be690dcdb9780a6b","modified":1621218117784,"created":1621218090350,"url":"http://{{ _.server }}:{{ _.puerto }}/api/pedido/1","name":"05-PedidoPorId","description":"","method":"GET","body":{},"parameters":[],"headers":[],"authentication":{},"metaSortKey":-1621001198689.75,"isPrivate":false,"settingStoreCookies":true,"settingSendCookies":true,"settingDisableRenderRequestBody":false,"settingEncodeUrl":true,"settingRebuildPath":true,"settingFollowRedirects":"global","_type":"request"},{"_id":"req_efceff2cbaad4e9fac46216f1037cb28","parentId":"fld_d7ea4760478a49c0be690dcdb9780a6b","modified":1621218170886,"created":1621218161725,"url":"http://{{ _.server }}:{{ _.puerto }}/api/pedido/1/detalle/1","name":"05-DetallePedidoPorId","description":"","method":"GET","body":{},"parameters":[],"headers":[],"authentication":{},"metaSortKey":-1620965661260.875,"isPrivate":false,"settingStoreCookies":true,"settingSendCookies":true,"settingDisableRenderRequestBody":false,"settingEncodeUrl":true,"settingRebuildPath":true,"settingFollowRedirects":"global","_type":"request"},{"_id":"env_0fb2b6ce54cbaf304b541872bd942f8fb076e939","parentId":"wrk_54d68373d3bd40dbba37866c210345ec","modified":1616439696066,"created":1616439696066,"name":"Base Environment","data":{},"dataPropertyOrder":null,"color":null,"isPrivate":false,"metaSortKey":1616439696066,"_type":"environment"},{"_id":"jar_0fb2b6ce54cbaf304b541872bd942f8fb076e939","parentId":"wrk_54d68373d3bd40dbba37866c210345ec","modified":1616439696069,"created":1616439696069,"name":"Default Jar","cookies":[],"_type":"cookie_jar"},{"_id":"spc_556195c245214126a9fdc4cfc3975dea","parentId":"wrk_54d68373d3bd40dbba37866c210345ec","modified":1616439695951,"created":1616439695951,"fileName":"Insomnia","contents":"","contentType":"yaml","_type":"api_spec"},{"_id":"env_a3094d1848dd4df1b6e070e2c0180bc2","parentId":"env_0fb2b6ce54cbaf304b541872bd942f8fb076e939","modified":1621214282673,"created":1621214251798,"name":"MS-PEDIDO","data":{"server":"localhost","puerto":"8081"},"dataPropertyOrder":{"&":["server","puerto"]},"color":"#ddcb0e","isPrivate":false,"metaSortKey":1620930689403,"_type":"environment"}]}